{
    "all": [],
    "warframe": [
        "warframe",
        "ash",
        "atlas",
        "banshee",
        "baruuk",
        "caliban",
        "chroma",
        "citrine",
        "ember",
        "equinox",
        "excalibur",
        "frost",
        "gara",
        "garuda",
        "gauss",
        "grendel",
        "gyre",
        "harrow",
        "hildryn",
        "hydroid",
        "inaros",
        "ivara",
        "khora",
        "kullervo",
        "lavos",
        "limbo",
        "loki",
        "mag",
        "mesa",
        "mirage",
        "nekros",
        "nezha",
        "nidus",
        "nova",
        "nyx",
        "oberon",
        "octavia",
        "protea",
        "revenant",
        "rhino",
        "saryn",
        "sevagoth",
        "styanax",
        "titania",
        "trinity",
        "valkyr",
        "vauban",
        "volt",
        "voruna",
        "wisp",
        "wukong",
        "xaku",
        "yareli",
        "zephyr"
    ],
    "primary": [
        "primary",
        "shotgun",
        "rifle",
        "sniper",
        "sobek",
        "argonak",
        "daikyu",
        "javlok",
        "rubico",
        "bow",
        "paris prime",
        "grakata",
        "tigris",
        "assault rifle",
        "mutalist quanta",
        "tiberon",
        "grinlok",
        "supra",
        "panthera",
        "bronco",
        "latron",
        "convectrix",
        "harpak",
        "hind",
        "flux rifle",
        "tetra",
        "drakgoon",
        "burston prime",
        "gorgon",
        "soma prime",
        "vulkar",
        "rifle (no aoe)",
        "penta",
        "miter",
        "ogris",
        "tonkor",
        "hek",
        "battacor",
        "sybaris",
        "burston",
        "lanka"
    ],
    "secondary": [
        "secondary",
        "pistol",
        "pistol (no aoe)",
        "thrown",
        "akbronco prime",
        "magnus",
        "despair",
        "bolto",
        "embolist",
        "zylok",
        "akjagara",
        "ocucor",
        "spectra",
        "marelok",
        "viper",
        "ballistica",
        "staticor",
        "kunai",
        "detron",
        "acrid",
        "furis",
        "akstiletto prime"
    ],
    "melee": [
        "melee",
        "furax",
        "ripkas",
        "dual daggers",
        "polearms",
        "glaives",
        "nunchaku",
        "silva & aegis",
        "jaw sword",
        "nikanas",
        "skana",
        "sparring",
        "gunblade",
        "whips",
        "dual swords",
        "heavy blade",
        "daggers",
        "hammers",
        "swords",
        "rapiers",
        "machetes",
        "assault saw",
        "staves",
        "thrown melee",
        "blade and whip",
        "ack & brunt",
        "sword and shield",
        "obex",
        "kestrel",
        "claws",
        "fists",
        "heavy scythe",
        "tonfas",
        "dark dagger",
        "dual cleavers",
        "dual nikanas",
        "scythes",
        "twin basolk",
        "warfans",
        "prova",
        "mire",
        "jat kittag",
        "two-handed nikana"
    ],
    "exilus": [],
    "aura": ["aura"],
    "robotic": [
        "robotic",
        "companion",
        "sentinel",
        "hound",
        "carrier",
        "dethcube",
        "diriga",
        "djinn",
        "helios",
        "nautilus",
        "oxylus",
        "shade",
        "taxon",
        "wyrm"
    ],
    "beast": [
        "beast",
        "companion",
        "sahasa kubrow",
        "raksa kubrow",
        "huras kubrow",
        "kubrow",
        "chesa kubrow",
        "sunika kubrow",
        "predasite",
        "vizier predasite",
        "pharaoh predasite",
        "medjay predasite",
        "kavat",
        "adarza kavat",
        "smeeta kavat",
        "vasca kavat",
        "vulpaphyla",
        "crescent vulpaphyla",
        "panzer vulpaphyla",
        "sly vulpaphyla",
        "helminth charger"
    ],
    "other": [
        "unique",
        " elytron",
        "k-drive",
        "archgun",
        "moa",
        "diriga",
        "archwing",
        "archmelee",
        "parazon",
        " itzal",
        "any",
        " odonata",
        "necramech",
        "mod",
        "helminth"
    ],
    "duplicates": []
}
